MANIFEST.in
README.md
setup.py
CKWeb.egg-info/PKG-INFO
CKWeb.egg-info/SOURCES.txt
CKWeb.egg-info/dependency_links.txt
CKWeb.egg-info/requires.txt
CKWeb.egg-info/top_level.txt
src/CKWeb/__init__.py
src/CKWeb/drivers.json