Metadata-Version: 1.0
Name: CKWeb
Version: 0.0.2b0
Summary: ChokChaisak
Home-page: https://github.com/ChokChaisak/ChokChaisak
Author: ChokChaisak
Author-email: ChokChaisak@gmail.com
License: ChokChaisak
Keywords: CKWeb
Platform: UNKNOWN
